zerox_sync/__init__.py
zerox_sync/constants/__init__.py
zerox_sync/constants/conversion.py
zerox_sync/constants/messages.py
zerox_sync/constants/prompts.py
zerox_sync/core/__init__.py
zerox_sync/core/types.py
zerox_sync/core/zerox.py
zerox_sync/errors/__init__.py
zerox_sync/errors/base.py
zerox_sync/errors/exceptions.py
zerox_sync/models/__init__.py
zerox_sync/models/gemini.py
zerox_sync/processor/__init__.py
zerox_sync/processor/image.py
zerox_sync/processor/pdf.py
zerox_sync/processor/text.py
zerox_sync/processor/utils.py
zerox_sync-0.2.0.dist-info/licenses/LICENSE
zerox_sync-0.2.0.dist-info/METADATA
zerox_sync-0.2.0.dist-info/WHEEL
zerox_sync-0.2.0.dist-info/top_level.txt
zerox_sync-0.2.0.dist-info/RECORD
