Metadata-Version: 2.4
Name: zerox-sync
Version: 0.2.0
Summary: Synchronous OCR using Gemini Vision API - A rewrite of pyzerox without async/litellm
Author-email: Claude <systems@lucidgreen.io>
License-Expression: MIT
Project-URL: Homepage, https://github.com/lucidgreen/zerox-sync
Project-URL: Documentation, https://github.com/yourusername/zerox-sync#readme
Project-URL: Repository, https://github.com/yourusername/zerox-sync
Project-URL: Issues, https://github.com/yourusername/zerox-sync/issues
Keywords: ocr,document-extraction,gemini,vision,pdf,markdown,ai,machine-learning
Classifier: Development Status :: 3 - Alpha
Classifier: Intended Audience :: Developers
Classifier: Programming Language :: Python :: 3
Classifier: Programming Language :: Python :: 3.9
Classifier: Programming Language :: Python :: 3.10
Classifier: Programming Language :: Python :: 3.11
Classifier: Programming Language :: Python :: 3.12
Classifier: Topic :: Scientific/Engineering :: Artificial Intelligence
Classifier: Topic :: Text Processing :: Markup :: Markdown
Requires-Python: >=3.9
License-File: LICENSE
Requires-Dist: google-genai>=0.1.0
Requires-Dist: pdf2image>=1.17.0
Requires-Dist: pypdf>=3.0.0
Requires-Dist: requests>=2.31.0
Provides-Extra: dev
Requires-Dist: pytest>=8.0.0; extra == "dev"
Requires-Dist: pytest-cov>=4.1.0; extra == "dev"
Requires-Dist: black>=24.0.0; extra == "dev"
Requires-Dist: ruff>=0.5.0; extra == "dev"
Requires-Dist: mypy>=1.8.0; extra == "dev"
Dynamic: license-file
